json_dict.py
Json_Dict-0.3.1615812759.dist-info/LICENSE.txt
Json_Dict-0.3.1615812759.dist-info/METADATA
Json_Dict-0.3.1615812759.dist-info/WHEEL
Json_Dict-0.3.1615812759.dist-info/top_level.txt
Json_Dict-0.3.1615812759.dist-info/RECORD
