Metadata-Version: 2.1
Name: Json-Dict
Version: 0.3.1615812759
Summary: Store data in JSON format
Home-page: https://github.com/JulianKimmig/json_dict
Author: Julian Kimmig
Author-email: julian-kimmig@gmx.net
License: UNKNOWN
Platform: UNKNOWN
Classifier: Programming Language :: Python :: 3
Classifier: License :: OSI Approved :: MIT License
Classifier: Operating System :: OS Independent
